biohit_pipettor_plus/__init__.py
biohit_pipettor_plus/deck_structure/__init__.py
biohit_pipettor_plus/deck_structure/control_json.py
biohit_pipettor_plus/deck_structure/deck.py
biohit_pipettor_plus/deck_structure/labware_classes/__init__.py
biohit_pipettor_plus/deck_structure/labware_classes/individualpipetteholder.py
biohit_pipettor_plus/deck_structure/labware_classes/labware.py
biohit_pipettor_plus/deck_structure/labware_classes/pipetteholder.py
biohit_pipettor_plus/deck_structure/labware_classes/plate.py
biohit_pipettor_plus/deck_structure/labware_classes/reservoir.py
biohit_pipettor_plus/deck_structure/labware_classes/reservoirHolder.py
biohit_pipettor_plus/deck_structure/labware_classes/stack.py
biohit_pipettor_plus/deck_structure/labware_classes/tipdropzone.py
biohit_pipettor_plus/deck_structure/labware_classes/well.py
biohit_pipettor_plus/deck_structure/position.py
biohit_pipettor_plus/deck_structure/serializable.py
biohit_pipettor_plus/deck_structure/slot.py
biohit_pipettor_plus/gui/__init__.py
biohit_pipettor_plus/gui/executioncontroloverlay.py
biohit_pipettor_plus/gui/function_window.py
biohit_pipettor_plus/gui/gui2.py
biohit_pipettor_plus/gui/gui_dialogs.py
biohit_pipettor_plus/gui/operations/__init__.py
biohit_pipettor_plus/gui/operations/executionresult.py
biohit_pipettor_plus/gui/operations/operation.py
biohit_pipettor_plus/gui/operations/operation_builder.py
biohit_pipettor_plus/gui/operations/operation_config.py
biohit_pipettor_plus/gui/operations/operation_logger.py
biohit_pipettor_plus/gui/operations/operation_session.py
biohit_pipettor_plus/gui/operations/operationtype.py
biohit_pipettor_plus/gui/operations/workflow.py
biohit_pipettor_plus/gui/operations/workflow_executor.py
biohit_pipettor_plus/gui/ui_helper.py
biohit_pipettor_plus/gui/well_window.py
biohit_pipettor_plus/pipettor_plus/__init__.py
biohit_pipettor_plus/pipettor_plus/config.py
biohit_pipettor_plus/pipettor_plus/errors.py
biohit_pipettor_plus/pipettor_plus/geometry.py
open_biohit_gui-1.0.4.dist-info/METADATA
open_biohit_gui-1.0.4.dist-info/WHEEL
open_biohit_gui-1.0.4.dist-info/entry_points.txt
open_biohit_gui-1.0.4.dist-info/licenses/LICENSE
open_biohit_gui-1.0.4.dist-info/RECORD
