Metadata-Version: 2.4
Name: open-biohit-gui
Version: 1.0.4
Summary: Designed to be used with pipettor_package following similar structure to open-biohit
License: MIT
License-File: LICENSE
Author: Advait Lath
Author-email: advaitlath1@gmail.com
Requires-Python: >=3.9,<3.11
Classifier: License :: OSI Approved :: MIT License
Classifier: Programming Language :: Python :: 3
Classifier: Programming Language :: Python :: 3.9
Classifier: Programming Language :: Python :: 3.10
Requires-Dist: kiwisolver (>=1.3.0,<1.4.0)
Requires-Dist: matplotlib (>=3.7.0,<3.8.0)
Requires-Dist: open-biohit (>=0.0.2,<0.0.3)
Requires-Dist: pillow (>=11.3.0,<12.0.0)
Requires-Dist: ttkbootstrap (>=1.10.0,<2.0.0)
Project-URL: Repository, https://github.com/smartlab-network/open-biohit-gui
